swimos/__init__.py
swimos/client/__init__.py
swimos/client/_connections.py
swimos/client/_swim_client.py
swimos/client/_utils.py
swimos/client/_downlinks/__init__.py
swimos/client/_downlinks/_downlinks.py
swimos/client/_downlinks/_utils.py
swimos/recon/__init__.py
swimos/recon/_parsers.py
swimos/recon/_recon.py
swimos/recon/_utils.py
swimos/recon/_writers.py
swimos/structures/__init__.py
swimos/structures/_structs.py
swimos/warp/__init__.py
swimos/warp/_warp.py
test/client/__init__.py
test/client/test_connections.py
test/client/test_swim_client.py
test/client/test_utils.py
test/client/downlinks/__init__.py
test/client/downlinks/test_downlink_utils.py
test/client/downlinks/test_downlinks.py
test/recon/__init__.py
test/recon/test_parsers.py
test/recon/test_recon.py
test/recon/test_utils.py
test/recon/test_writers.py
test/structures/__init__.py
test/structures/test_structs.py
test/warp/__init__.py
test/warp/test_envelope_parse.py
test/warp/test_envelope_write.py
test/warp/test_envelopes.py
test/warp/test_forms.py
swimos-1.6.0a0.dist-info/LICENSE
swimos-1.6.0a0.dist-info/METADATA
swimos-1.6.0a0.dist-info/WHEEL
swimos-1.6.0a0.dist-info/top_level.txt
swimos-1.6.0a0.dist-info/RECORD
