Metadata-Version: 2.1
Name: swimos
Version: 1.6.0a0
Summary: Standalone Python framework for building massively real-time streaming WARP clients.
Home-page: https://github.com/swimos/swim-system-python
Author: Dobromir Marinov
Author-email: dobromir@swim.it
Keywords: swim client
Classifier: Programming Language :: Python :: 3
Classifier: Development Status :: 3 - Alpha
Classifier: Intended Audience :: Developers
Classifier: License :: OSI Approved :: Apache Software License
Classifier: Operating System :: OS Independent
License-File: LICENSE
Requires-Dist: websockets
